colcon_rerun/__init__.py
colcon_rerun/config.py
colcon_rerun/logging.py
colcon_rerun/argument_parser/__init__.py
colcon_rerun/argument_parser/rerun.py
colcon_rerun/verb/__init__.py
colcon_rerun/verb/rerun.py
colcon_rerun-0.1.1.dist-info/LICENSE
colcon_rerun-0.1.1.dist-info/METADATA
colcon_rerun-0.1.1.dist-info/WHEEL
colcon_rerun-0.1.1.dist-info/entry_points.txt
colcon_rerun-0.1.1.dist-info/top_level.txt
colcon_rerun-0.1.1.dist-info/zip-safe
colcon_rerun-0.1.1.dist-info/RECORD
